[{"timestamp": "2026-01-03T23:53:24.995312", "anchors": [12, 2], "confidence": 0.8, "hit": null}, {"timestamp": "2026-01-03T23:53:26.479303", "anchors": [12, 2], "confidence": 0.8, "hit": null}, {"timestamp": "2026-01-03T23:53:36.978293", "anchors": [12, 2], "confidence": 0.8, "hit": null}, {"timestamp": "2026-01-03T23:53:41.480929", "anchors": [12, 2], "confidence": 0.8, "hit": null}, {"timestamp": "2026-01-03T23:53:47.480468", "anchors": [7, 17, 12, 2], "confidence": 0.8, "hit": null}, {"timestamp": "2026-01-03T23:57:14.492128", "anchors": [16, 4, 19, 2], "confidence": 0.8, "hit": null}, {"timestamp": "2026-01-03T23:57:17.485788", "anchors": [16, 2, 0, 4], "confidence": 0.85, "hit": null}, {"timestamp": "2026-01-03T23:57:18.985032", "anchors": [1, 2, 0, 3], "confidence": 0.85, "hit": null}, {"timestamp": "2026-01-03T23:57:21.981631", "anchors": [2, 1, 0, 14], "confidence": 0.85, "hit": null}, {"timestamp": "2026-01-03T23:57:23.485775", "anchors": [2, 1, 0, 14], "confidence": 0.85, "hit": null}, {"timestamp": "2026-01-04T00:06:20.369870", "anchors": [12, 2], "confidence": 0.7000000000000001, "hit": false}, {"timestamp": "2026-01-04T00:06:23.352643", "anchors": [12, 2], "confidence": 0.7000000000000001, "hit": false}, {"timestamp": "2026-01-04T00:06:29.357658", "anchors": [12, 2], "confidence": 0.7000000000000001, "hit": false}, {"timestamp": "2026-01-04T00:06:35.355549", "anchors": [7, 17, 12, 2], "confidence": 0.7000000000000001, "hit": null}, {"timestamp": "2026-01-04T00:06:39.855276", "anchors": [7, 17, 32, 8], "confidence": 0.75, "hit": null}, {"timestamp": "2026-01-04T00:07:00.857386", "anchors": [7, 17, 32, 24], "confidence": 0.75, "hit": null}, {"timestamp": "2026-01-04T00:07:03.859868", "anchors": [7, 6, 8, 17], "confidence": 0.75, "hit": null}, {"timestamp": "2026-01-04T00:07:08.356860", "anchors": [7, 6, 5, 8], "confidence": 0.75, "hit": null}, {"timestamp": "2026-01-04T00:07:09.862820", "anchors": [6, 5, 7, 9], "confidence": 0.75, "hit": null}, {"timestamp": "2026-01-04T00:07:17.355162", "anchors": [6, 3, 5, 7], "confidence": 0.75, "hit": null}, {"timestamp": "2026-01-04T00:09:35.359214", "anchors": [6, 8, 3, 5], "confidence": 0.75, "hit": null}, {"timestamp": "2026-01-04T00:09:36.858169", "anchors": [6, 11, 8, 12], "confidence": 0.75, "hit": null}, {"timestamp": "2026-01-04T00:09:38.362172", "anchors": [12, 11, 13, 10], "confidence": 0.75, "hit": null}, {"timestamp": "2026-01-04T00:09:39.858796", "anchors": [12, 13, 11, 10], "confidence": 0.75, "hit": null}, {"timestamp": "2026-01-04T00:09:41.356266", "anchors": [12, 13, 11, 10], "confidence": 0.75, "hit": null}, {"timestamp": "2026-01-04T00:09:42.854074", "anchors": [12, 13, 11, 10], "confidence": 0.75, "hit": null}, {"timestamp": "2026-01-04T00:09:44.355563", "anchors": [12, 13, 11, 10], "confidence": 0.75, "hit": null}, {"timestamp": "2026-01-04T00:09:45.898140", "anchors": [12, 13, 11, 10], "confidence": 0.75, "hit": null}, {"timestamp": "2026-01-04T00:09:47.361042", "anchors": [12, 13, 11, 10], "confidence": 0.75, "hit": null}, {"timestamp": "2026-01-04T00:09:48.853787", "anchors": [12, 13, 11, 10], "confidence": 0.75, "hit": null}, {"timestamp": "2026-01-04T00:14:20.022015", "anchors": [9, 23], "confidence": 0.7000000000000001, "hit": false}, {"timestamp": "2026-01-04T00:14:26.016331", "anchors": [9, 23, 3], "confidence": 0.75, "hit": false}, {"timestamp": "2026-01-04T00:14:32.016414", "anchors": [9, 23, 3], "confidence": 0.75, "hit": true}, {"timestamp": "2026-01-04T00:14:36.513625", "anchors": [9, 23, 3], "confidence": 0.75, "hit": false}, {"timestamp": "2026-01-04T00:14:41.018771", "anchors": [9, 23, 3], "confidence": 0.75, "hit": true}, {"timestamp": "2026-01-04T00:17:45.520719", "anchors": [10, 13], "confidence": 0.7000000000000001, "hit": false}, {"timestamp": "2026-01-04T00:17:48.518256", "anchors": [14, 3, 10, 13], "confidence": 0.7000000000000001, "hit": null}, {"timestamp": "2026-01-04T00:17:50.015317", "anchors": [14, 3, 17, 10], "confidence": 0.7000000000000001, "hit": false}, {"timestamp": "2026-01-04T00:18:00.517256", "anchors": [17, 4, 14, 3], "confidence": 0.75, "hit": false}, {"timestamp": "2026-01-04T00:18:06.516962", "anchors": [4, 17, 18, 22], "confidence": 0.75, "hit": null}, {"timestamp": "2026-01-10T06:55:52.920023", "anchors": [12, 2], "confidence": 0.7000000000000001, "hit": false}, {"timestamp": "2026-01-10T06:55:54.413796", "anchors": [12, 2], "confidence": 0.7000000000000001, "hit": false}, {"timestamp": "2026-01-10T07:04:13.263673", "anchors": [12, 2], "confidence": 0.7000000000000001, "hit": false}, {"timestamp": "2026-01-10T07:04:17.759776", "anchors": [12, 2], "confidence": 0.7000000000000001, "hit": false}, {"timestamp": "2026-01-10T07:05:22.123399", "anchors": [12, 2], "confidence": 0.7000000000000001, "hit": false}, {"timestamp": "2026-01-10T07:05:25.116476", "anchors": [12, 2], "confidence": 0.7000000000000001, "hit": null}, {"timestamp": "2026-01-10T07:05:34.118361", "anchors": [12, 2], "confidence": 0.7000000000000001, "hit": null}, {"timestamp": "2026-01-10T07:06:13.118862", "anchors": [12, 2], "confidence": 0.7000000000000001, "hit": false}, {"timestamp": "2026-01-10T07:09:55.663144", "anchors": [12, 2], "confidence": 0.7000000000000001, "hit": false}, {"timestamp": "2026-01-10T07:10:01.660756", "anchors": [12, 2], "confidence": 0.7000000000000001, "hit": null}, {"timestamp": "2026-01-10T07:15:11.444325", "anchors": [12, 2], "confidence": 0.7000000000000001, "hit": null}, {"timestamp": "2026-01-10T07:15:12.937026", "anchors": [12, 2], "confidence": 0.7000000000000001, "hit": false}, {"timestamp": "2026-01-10T07:15:18.937110", "anchors": [12, 2], "confidence": 0.7000000000000001, "hit": false}, {"timestamp": "2026-01-10T07:26:35.088275", "anchors": [12, 2], "confidence": 0.7000000000000001, "hit": false}, {"timestamp": "2026-01-10T07:27:08.091454", "anchors": [12, 2], "confidence": 0.7000000000000001, "hit": false}, {"timestamp": "2026-01-10T07:27:14.072475", "anchors": [12, 2], "confidence": 0.7000000000000001, "hit": false}, {"timestamp": "2026-01-10T07:27:24.570442", "anchors": [7, 17, 12, 2], "confidence": 0.7000000000000001, "hit": null}, {"timestamp": "2026-01-10T07:27:33.570116", "anchors": [7, 17, 32, 8], "confidence": 0.75, "hit": true}, {"timestamp": "2026-01-10T07:27:41.071647", "anchors": [7, 17, 32, 24], "confidence": 0.75, "hit": null}, {"timestamp": "2026-01-10T07:27:59.073788", "anchors": [7, 17, 32, 8], "confidence": 0.75, "hit": null}, {"timestamp": "2026-01-10T07:28:41.531552", "anchors": [12, 2], "confidence": 0.7000000000000001, "hit": false}, {"timestamp": "2026-01-10T07:28:47.524338", "anchors": [12, 2], "confidence": 0.7000000000000001, "hit": false}, {"timestamp": "2026-01-10T07:28:52.024003", "anchors": [12, 2], "confidence": 0.7000000000000001, "hit": false}, {"timestamp": "2026-01-10T07:28:55.024731", "anchors": [7, 17, 12, 2], "confidence": 0.7000000000000001, "hit": null}, {"timestamp": "2026-01-10T07:30:29.533226", "anchors": [7, 17, 32, 8], "confidence": 0.75, "hit": true}, {"timestamp": "2026-01-10T07:30:38.521194", "anchors": [7, 17, 32, 24], "confidence": 0.75, "hit": false}, {"timestamp": "2026-01-10T07:31:17.521860", "anchors": [7, 6, 8, 17], "confidence": 0.75, "hit": true}]